Workbook

Sheet 情境輸入
A1: 情境及成本輸入
A2: Millie Beau Limited 2026-10-11 港幣；藍字為可修改假設，並非本案法院估值或報價。
A4: 情境 | B4: 程度 | C4: 程序分支 | D4: PSLA假設 | E4: 其他損失假設 | F4: 自方法律 | G4: 專家成本 | H4: 管理小時 | I4: 每小時成本 | J4: 溝通成本 | K4: 對方成本 | L4: 來源／限制 | M4: 確認保險貢獻
A5: A | B5: 低 | C5: 小額 | D5: 0 | E5: 0 | F5: 2000 | G5: 0 | H5: 6 | I5: 300 | J5: 0 | K5: 0 | L5: 假設人傷及其他申索均無應付款，獨立套餐責任須另計。
A6: A | B6: 中 | C6: 小額 | D6: 0 | E6: 0 | F6: 5000 | G6: 5000 | H6: 12 | I6: 300 | J6: 1000 | K6: 0 | L6: 假設人傷及其他申索均無應付款，獨立套餐責任須另計。
A7: A | B7: 高 | C7: 小額 | D7: 0 | E7: 0 | F7: 10000 | G7: 10000 | H7: 24 | I7: 300 | J7: 3000 | K7: 0 | L7: 假設人傷及其他申索均無應付款，獨立套餐責任須另計。
A8: B | B8: 低 | C8: 小額 | D8: 9000 | E8: 1000 | F8: 2000 | G8: 0 | H8: 6 | I8: 300 | J8: 0 | K8: 500 | L8: 純敏感度假設，沒有匹配判例；小額對方成本只指程序開支。
A9: B | B9: 中 | C9: 小額 | D9: 24000 | E9: 1000 | F9: 5000 | G9: 5000 | H9: 12 | I9: 300 | J9: 1000 | K9: 2000 | L9: 純敏感度假設，沒有匹配判例；小額對方成本只指程序開支。
A10: B | B10: 高 | C10: 小額 | D10: 55000 | E10: 5000 | F10: 10000 | G10: 10000 | H10: 24 | I10: 300 | J10: 3000 | K10: 5000 | L10: 純敏感度假設，沒有匹配判例；小額對方成本只指程序開支。
A11: C | B11: 低 | C11: 區院 | D11: 75000 | E11: 5000 | F11: 40000 | G11: 10000 | H11: 20 | I11: 300 | J11: 2000 | K11: 30000 | L11: PSLA採歷史判例參考，其他損失及成本是假設，未作2026調整。
A12: C | B12: 中 | C12: 區院 | D12: 120000 | E12: 20000 | F12: 100000 | G12: 25000 | H12: 50 | I12: 300 | J12: 5000 | K12: 80000 | L12: PSLA採歷史判例參考，其他損失及成本是假設，未作2026調整。
A13: C | B13: 高 | C13: 區院 | D13: 200000 | E13: 80000 | F13: 250000 | G13: 60000 | H13: 100 | I13: 300 | J13: 15000 | K13: 200000 | L13: PSLA採歷史判例參考，其他損失及成本是假設，未作2026調整。
A14: D | B14: 低 | C14: 區院 | D14: 200000 | E14: 100000 | F14: 40000 | G14: 10000 | H14: 20 | I14: 300 | J14: 2000 | K14: 30000 | L14: 嚴重後果資金壓力測試，未證明本案有功能、收入或精神科損失。
A15: D | B15: 中 | C15: 區院 | D15: 300000 | E15: 200000 | F15: 100000 | G15: 25000 | H15: 50 | I15: 300 | J15: 5000 | K15: 80000 | L15: 嚴重後果資金壓力測試，未證明本案有功能、收入或精神科損失。
A16: D | B16: 高 | C16: 區院 | D16: 300000 | E16: 550000 | F16: 250000 | G16: 60000 | H16: 100 | I16: 300 | J16: 15000 | K16: 200000 | L16: 嚴重後果資金壓力測試，未證明本案有功能、收入或精神科損失。
A19: 決策輸入 | B19: 數值 | C19: 單位 | D19: 說明
A20: 擬比較和解金 | B20: 25000 | C20: HKD | D20: 只是客戶提出金額，未接受或提出要約。
A21: 結案成本低 | B21: 2000 | C21: HKD | D21: 管理預算，替換成實際報價。
A22: 結案成本中 | B22: 7000 | C22: HKD | D22: 管理預算，替換成實際報價。
A23: 結案成本高 | B23: 15000 | C23: HKD | D23: 管理預算，替換成實際報價。
A24: 敗訴機率 p | C24: 0–1 | D24: 須由經核實證據及法律意見判斷；空白不等於0。
A25: 進入訴訟機率 q | C25: 0–1 | D25: 拒絕方案的訴訟概率，未知時不算期望成本。
A26: 勝訴可實收成本 R | C26: HKD | D26: 填預期實際回收額而非紙面訟費令；小額不得填區院律師費。
A27: 確認和解保險貢獻低 | C27: HKD | D27: 只填已確認在相應和解分支支付的賠償及費用，不明保持空白。
A28: 確認和解保險貢獻中 | C28: HKD | D28: 承保、免賠、限額及分項確認後填寫；各情境的保險額另填上方M欄。
A29: 確認和解保險貢獻高 | C29: HKD | D29: 不得重複抵扣已由保險支付的費用。
A30: 核實醫療預付款 M | C30: HKD | D30: 從受限記錄填入必要金額；付款仍需批准，未必結案。
A31: 短期調查成本低 | B31: 7000 | C31: HKD | D31: 只計增量調查，不包含其後結案或訴訟。
A32: 短期調查成本中 | B32: 15000 | C32: HKD | D32: 管理預算。
A33: 短期調查成本高 | B33: 30000 | C33: HKD | D33: 管理預算。
A34: 醫療處理成本低 | B34: 2000 | C34: HKD | D34: 管理預算；尚有未解除申索。
A35: 醫療處理成本中 | B35: 5000 | C35: HKD | D35: 管理預算。
A36: 醫療處理成本高 | B36: 10000 | C36: HKD | D36: 管理預算。
A37: 拒絕即時調查 F0 | C37: HKD | D37: 與訴訟增量抗辯費分開，不能重複計算。
A38: 增量訴訟成本 F | C38: HKD | D38: 按實際程序取得報價；未填不計期望額。
A39: 敗訴賠償 D | C39: HKD | D39: 需個別估值，不能直接用歷史案例。
A40: 敗訴對方成本 A | C40: HKD | D40: 按實際程序，不把小額案當區院。
A41: 其他業務成本 | C41: HKD | D41: 只計可核實增量成本或損失毛利，避免與工時／溝通重複。

Sheet 情境支出
A1: 四種情境支出
A2: 保險前資金壓力測試，並非賠償預測；勝訴成本仍會發生。保險未確認時淨額顯示待確認。
A4: 情境 | B4: 程度 | C4: 程序分支 | D4: 假設賠償 | E4: 管理成本 | F4: 自方總成本 | G4: 對方成本 | H4: 敗訴總支出 | I4: 確認保險貢獻 | J4: 公司淨支出
A5: A | B5: 低 | C5: ='情境輸入'!C5 -> 小額 | D5: =IF(COUNT('情境輸入'!D5:E5)=2,SUM('情境輸入'!D5:E5),"待填損失") -> 0 | E5: =IF(COUNT('情境輸入'!H5:I5)=2,'情境輸入'!H5*'情境輸入'!I5,"待填工時") -> 1800 | F5: =IF(COUNT('情境輸入'!F5:G5,'情境輸入'!J5,E5)=4,SUM('情境輸入'!F5:G5,'情境輸入'!J5,E5),"待填成本") -> 3800 | G5: =IF(COUNT('情境輸入'!K5)=1,'情境輸入'!K5,"待填對方成本") -> 0 | H5: =IF(COUNT(D5,F5,G5)=3,SUM(D5,F5,G5),"待填分項") -> 3800 | I5: =IF(COUNT('情境輸入'!M5)=1,'情境輸入'!M5,"待確認") -> 待確認 | J5: =IF(COUNT(H5,I5)=2,IF(I5<=H5,H5-I5,"保險額超總支出"),"待確認保險") -> 待確認保險
A6: A | B6: 中 | C6: ='情境輸入'!C6 -> 小額 | D6: =IF(COUNT('情境輸入'!D6:E6)=2,SUM('情境輸入'!D6:E6),"待填損失") -> 0 | E6: =IF(COUNT('情境輸入'!H6:I6)=2,'情境輸入'!H6*'情境輸入'!I6,"待填工時") -> 3600 | F6: =IF(COUNT('情境輸入'!F6:G6,'情境輸入'!J6,E6)=4,SUM('情境輸入'!F6:G6,'情境輸入'!J6,E6),"待填成本") -> 14600 | G6: =IF(COUNT('情境輸入'!K6)=1,'情境輸入'!K6,"待填對方成本") -> 0 | H6: =IF(COUNT(D6,F6,G6)=3,SUM(D6,F6,G6),"待填分項") -> 14600 | I6: =IF(COUNT('情境輸入'!M6)=1,'情境輸入'!M6,"待確認") -> 待確認 | J6: =IF(COUNT(H6,I6)=2,IF(I6<=H6,H6-I6,"保險額超總支出"),"待確認保險") -> 待確認保險
A7: A | B7: 高 | C7: ='情境輸入'!C7 -> 小額 | D7: =IF(COUNT('情境輸入'!D7:E7)=2,SUM('情境輸入'!D7:E7),"待填損失") -> 0 | E7: =IF(COUNT('情境輸入'!H7:I7)=2,'情境輸入'!H7*'情境輸入'!I7,"待填工時") -> 7200 | F7: =IF(COUNT('情境輸入'!F7:G7,'情境輸入'!J7,E7)=4,SUM('情境輸入'!F7:G7,'情境輸入'!J7,E7),"待填成本") -> 30200 | G7: =IF(COUNT('情境輸入'!K7)=1,'情境輸入'!K7,"待填對方成本") -> 0 | H7: =IF(COUNT(D7,F7,G7)=3,SUM(D7,F7,G7),"待填分項") -> 30200 | I7: =IF(COUNT('情境輸入'!M7)=1,'情境輸入'!M7,"待確認") -> 待確認 | J7: =IF(COUNT(H7,I7)=2,IF(I7<=H7,H7-I7,"保險額超總支出"),"待確認保險") -> 待確認保險
A8: B | B8: 低 | C8: ='情境輸入'!C8 -> 小額 | D8: =IF(COUNT('情境輸入'!D8:E8)=2,SUM('情境輸入'!D8:E8),"待填損失") -> 10000 | E8: =IF(COUNT('情境輸入'!H8:I8)=2,'情境輸入'!H8*'情境輸入'!I8,"待填工時") -> 1800 | F8: =IF(COUNT('情境輸入'!F8:G8,'情境輸入'!J8,E8)=4,SUM('情境輸入'!F8:G8,'情境輸入'!J8,E8),"待填成本") -> 3800 | G8: =IF(COUNT('情境輸入'!K8)=1,'情境輸入'!K8,"待填對方成本") -> 500 | H8: =IF(COUNT(D8,F8,G8)=3,SUM(D8,F8,G8),"待填分項") -> 14300 | I8: =IF(COUNT('情境輸入'!M8)=1,'情境輸入'!M8,"待確認") -> 待確認 | J8: =IF(COUNT(H8,I8)=2,IF(I8<=H8,H8-I8,"保險額超總支出"),"待確認保險") -> 待確認保險
A9: B | B9: 中 | C9: ='情境輸入'!C9 -> 小額 | D9: =IF(COUNT('情境輸入'!D9:E9)=2,SUM('情境輸入'!D9:E9),"待填損失") -> 25000 | E9: =IF(COUNT('情境輸入'!H9:I9)=2,'情境輸入'!H9*'情境輸入'!I9,"待填工時") -> 3600 | F9: =IF(COUNT('情境輸入'!F9:G9,'情境輸入'!J9,E9)=4,SUM('情境輸入'!F9:G9,'情境輸入'!J9,E9),"待填成本") -> 14600 | G9: =IF(COUNT('情境輸入'!K9)=1,'情境輸入'!K9,"待填對方成本") -> 2000 | H9: =IF(COUNT(D9,F9,G9)=3,SUM(D9,F9,G9),"待填分項") -> 41600 | I9: =IF(COUNT('情境輸入'!M9)=1,'情境輸入'!M9,"待確認") -> 待確認 | J9: =IF(COUNT(H9,I9)=2,IF(I9<=H9,H9-I9,"保險額超總支出"),"待確認保險") -> 待確認保險
A10: B | B10: 高 | C10: ='情境輸入'!C10 -> 小額 | D10: =IF(COUNT('情境輸入'!D10:E10)=2,SUM('情境輸入'!D10:E10),"待填損失") -> 60000 | E10: =IF(COUNT('情境輸入'!H10:I10)=2,'情境輸入'!H10*'情境輸入'!I10,"待填工時") -> 7200 | F10: =IF(COUNT('情境輸入'!F10:G10,'情境輸入'!J10,E10)=4,SUM('情境輸入'!F10:G10,'情境輸入'!J10,E10),"待填成本") -> 30200 | G10: =IF(COUNT('情境輸入'!K10)=1,'情境輸入'!K10,"待填對方成本") -> 5000 | H10: =IF(COUNT(D10,F10,G10)=3,SUM(D10,F10,G10),"待填分項") -> 95200 | I10: =IF(COUNT('情境輸入'!M10)=1,'情境輸入'!M10,"待確認") -> 待確認 | J10: =IF(COUNT(H10,I10)=2,IF(I10<=H10,H10-I10,"保險額超總支出"),"待確認保險") -> 待確認保險
A11: C | B11: 低 | C11: ='情境輸入'!C11 -> 區院 | D11: =IF(COUNT('情境輸入'!D11:E11)=2,SUM('情境輸入'!D11:E11),"待填損失") -> 80000 | E11: =IF(COUNT('情境輸入'!H11:I11)=2,'情境輸入'!H11*'情境輸入'!I11,"待填工時") -> 6000 | F11: =IF(COUNT('情境輸入'!F11:G11,'情境輸入'!J11,E11)=4,SUM('情境輸入'!F11:G11,'情境輸入'!J11,E11),"待填成本") -> 58000 | G11: =IF(COUNT('情境輸入'!K11)=1,'情境輸入'!K11,"待填對方成本") -> 30000 | H11: =IF(COUNT(D11,F11,G11)=3,SUM(D11,F11,G11),"待填分項") -> 168000 | I11: =IF(COUNT('情境輸入'!M11)=1,'情境輸入'!M11,"待確認") -> 待確認 | J11: =IF(COUNT(H11,I11)=2,IF(I11<=H11,H11-I11,"保險額超總支出"),"待確認保險") -> 待確認保險
A12: C | B12: 中 | C12: ='情境輸入'!C12 -> 區院 | D12: =IF(COUNT('情境輸入'!D12:E12)=2,SUM('情境輸入'!D12:E12),"待填損失") -> 140000 | E12: =IF(COUNT('情境輸入'!H12:I12)=2,'情境輸入'!H12*'情境輸入'!I12,"待填工時") -> 15000 | F12: =IF(COUNT('情境輸入'!F12:G12,'情境輸入'!J12,E12)=4,SUM('情境輸入'!F12:G12,'情境輸入'!J12,E12),"待填成本") -> 145000 | G12: =IF(COUNT('情境輸入'!K12)=1,'情境輸入'!K12,"待填對方成本") -> 80000 | H12: =IF(COUNT(D12,F12,G12)=3,SUM(D12,F12,G12),"待填分項") -> 365000 | I12: =IF(COUNT('情境輸入'!M12)=1,'情境輸入'!M12,"待確認") -> 待確認 | J12: =IF(COUNT(H12,I12)=2,IF(I12<=H12,H12-I12,"保險額超總支出"),"待確認保險") -> 待確認保險
A13: C | B13: 高 | C13: ='情境輸入'!C13 -> 區院 | D13: =IF(COUNT('情境輸入'!D13:E13)=2,SUM('情境輸入'!D13:E13),"待填損失") -> 280000 | E13: =IF(COUNT('情境輸入'!H13:I13)=2,'情境輸入'!H13*'情境輸入'!I13,"待填工時") -> 30000 | F13: =IF(COUNT('情境輸入'!F13:G13,'情境輸入'!J13,E13)=4,SUM('情境輸入'!F13:G13,'情境輸入'!J13,E13),"待填成本") -> 355000 | G13: =IF(COUNT('情境輸入'!K13)=1,'情境輸入'!K13,"待填對方成本") -> 200000 | H13: =IF(COUNT(D13,F13,G13)=3,SUM(D13,F13,G13),"待填分項") -> 835000 | I13: =IF(COUNT('情境輸入'!M13)=1,'情境輸入'!M13,"待確認") -> 待確認 | J13: =IF(COUNT(H13,I13)=2,IF(I13<=H13,H13-I13,"保險額超總支出"),"待確認保險") -> 待確認保險
A14: D | B14: 低 | C14: ='情境輸入'!C14 -> 區院 | D14: =IF(COUNT('情境輸入'!D14:E14)=2,SUM('情境輸入'!D14:E14),"待填損失") -> 300000 | E14: =IF(COUNT('情境輸入'!H14:I14)=2,'情境輸入'!H14*'情境輸入'!I14,"待填工時") -> 6000 | F14: =IF(COUNT('情境輸入'!F14:G14,'情境輸入'!J14,E14)=4,SUM('情境輸入'!F14:G14,'情境輸入'!J14,E14),"待填成本") -> 58000 | G14: =IF(COUNT('情境輸入'!K14)=1,'情境輸入'!K14,"待填對方成本") -> 30000 | H14: =IF(COUNT(D14,F14,G14)=3,SUM(D14,F14,G14),"待填分項") -> 388000 | I14: =IF(COUNT('情境輸入'!M14)=1,'情境輸入'!M14,"待確認") -> 待確認 | J14: =IF(COUNT(H14,I14)=2,IF(I14<=H14,H14-I14,"保險額超總支出"),"待確認保險") -> 待確認保險
A15: D | B15: 中 | C15: ='情境輸入'!C15 -> 區院 | D15: =IF(COUNT('情境輸入'!D15:E15)=2,SUM('情境輸入'!D15:E15),"待填損失") -> 500000 | E15: =IF(COUNT('情境輸入'!H15:I15)=2,'情境輸入'!H15*'情境輸入'!I15,"待填工時") -> 15000 | F15: =IF(COUNT('情境輸入'!F15:G15,'情境輸入'!J15,E15)=4,SUM('情境輸入'!F15:G15,'情境輸入'!J15,E15),"待填成本") -> 145000 | G15: =IF(COUNT('情境輸入'!K15)=1,'情境輸入'!K15,"待填對方成本") -> 80000 | H15: =IF(COUNT(D15,F15,G15)=3,SUM(D15,F15,G15),"待填分項") -> 725000 | I15: =IF(COUNT('情境輸入'!M15)=1,'情境輸入'!M15,"待確認") -> 待確認 | J15: =IF(COUNT(H15,I15)=2,IF(I15<=H15,H15-I15,"保險額超總支出"),"待確認保險") -> 待確認保險
A16: D | B16: 高 | C16: ='情境輸入'!C16 -> 區院 | D16: =IF(COUNT('情境輸入'!D16:E16)=2,SUM('情境輸入'!D16:E16),"待填損失") -> 850000 | E16: =IF(COUNT('情境輸入'!H16:I16)=2,'情境輸入'!H16*'情境輸入'!I16,"待填工時") -> 30000 | F16: =IF(COUNT('情境輸入'!F16:G16,'情境輸入'!J16,E16)=4,SUM('情境輸入'!F16:G16,'情境輸入'!J16,E16),"待填成本") -> 355000 | G16: =IF(COUNT('情境輸入'!K16)=1,'情境輸入'!K16,"待填對方成本") -> 200000 | H16: =IF(COUNT(D16,F16,G16)=3,SUM(D16,F16,G16),"待填分項") -> 1405000 | I16: =IF(COUNT('情境輸入'!M16)=1,'情境輸入'!M16,"待確認") -> 待確認 | J16: =IF(COUNT(H16,I16)=2,IF(I16<=H16,H16-I16,"保險額超總支出"),"待確認保險") -> 待確認保險
A19: A：零人傷及其他付款假設；B：短暫完全康復；C：持續色差／疤痕；D：嚴重後果。
A20: 上述成本不包括未填的其他業務成本、利息、上訴及執行。資料增加後另計，不能當最高上限。

Sheet 方案比較
A1: 處理方案及臨界機率
A2: 未知輸入不代入0；敏感度示例只作算術比較。所有付款、要約及對外行動仍需公司批准。
A4: 方案 | B4: 低 | C4: 中 | D4: 高 | E4: 限制／處理方式
A5: 25,000結案 | B5: =IF(COUNT('情境輸入'!B20,'情境輸入'!B21)=2,'情境輸入'!B20+'情境輸入'!B21,"待填") -> 27000 | C5: =IF(COUNT('情境輸入'!B20,'情境輸入'!B22)=2,'情境輸入'!B20+'情境輸入'!B22,"待填") -> 32000 | D5: =IF(COUNT('情境輸入'!B20,'情境輸入'!B23)=2,'情境輸入'!B20+'情境輸入'!B23,"待填") -> 40000 | E5: 包括假設結案費，未含未確認保險；需適當有效解除。
A6: 短期調查 | B6: ='情境輸入'!B31 -> 7000 | C6: ='情境輸入'!B32 -> 15000 | D6: ='情境輸入'!B33 -> 30000 | E6: 另加其後結案或訴訟增量成本；不要與自方成本重複。
A7: 醫療預付款及處理 | B7: =IF(COUNT('情境輸入'!B30,'情境輸入'!B34)=2,'情境輸入'!B30+'情境輸入'!B34,"待填核實醫療") -> 待填核實醫療 | C7: =IF(COUNT('情境輸入'!B30,'情境輸入'!B35)=2,'情境輸入'!B30+'情境輸入'!B35,"待填核實醫療") -> 待填核實醫療 | D7: =IF(COUNT('情境輸入'!B30,'情境輸入'!B36)=2,'情境輸入'!B30+'情境輸入'!B36,"待填核實醫療") -> 待填核實醫療 | E7: 未解除的申索仍可能產生成本；核實金額留空。
A8: 和解公司淨支出 | B8: =IF(COUNT(B5,'情境輸入'!B27)=2,IF('情境輸入'!B27<=B5,B5-'情境輸入'!B27,"保險額超總支出"),"待確認保險") -> 待確認保險 | C8: =IF(COUNT(C5,'情境輸入'!B28)=2,IF('情境輸入'!B28<=C5,C5-'情境輸入'!B28,"保險額超總支出"),"待確認保險") -> 待確認保險 | D8: =IF(COUNT(D5,'情境輸入'!B29)=2,IF('情境輸入'!B29<=D5,D5-'情境輸入'!B29,"保險額超總支出"),"待確認保險") -> 待確認保險 | E8: 各和解分支扣已確認保險貢獻；不明時保持待確認。
A9: 進入訴訟後期望成本 | B9: =IF(COUNT('情境輸入'!B24,'情境輸入'!B26,'情境輸入'!B38:B40)=5,'情境輸入'!B38+'情境輸入'!B24*('情境輸入'!B39+'情境輸入'!B40)-(1-'情境輸入'!B24)*'情境輸入'!B26,"待填p/F/D/A/R") -> 待填p/F/D/A/R | E9: F+p×(D+A)−(1−p)×R，保險前，與情境表分開。
A10: 拒絕方案期望成本 | B10: =IF(COUNT('情境輸入'!B25,'情境輸入'!B37,B9)=3,'情境輸入'!B37+'情境輸入'!B25*B9,"待填q/F0/訴訟額") -> 待填q/F0/訴訟額 | E10: F0+q×訴訟期望額；q未填不計。
A11: 其他業務成本 | B11: =IF(COUNT('情境輸入'!B41)=1,'情境輸入'!B41,"待核實") -> 待核實 | E11: 額外一項，只有已核實且未重複計入的成本才填。
A12: 與中位結案比較的臨界p | B12: =IF(COUNT(C5,'情境輸入'!B26,'情境輸入'!B38:B40)=5,IF(SUM('情境輸入'!B39:B40,'情境輸入'!B26)>0,(C5-'情境輸入'!B38+'情境輸入'!B26)/SUM('情境輸入'!B39:B40,'情境輸入'!B26),"無可用分母"),"待填F/D/A/R") -> 待填F/D/A/R | E12: (S−F+R)/(D+A+R)。小於0：假設下和解較便宜；大於1：抗辯較便宜。
A15: 算術示例 | B15: S結案總額 | C15: F自方成本 | D15: D賠償 | E15: A對方成本；R=0
A16: 小額成本5,000 | B16: 27000 | C16: 5000 | D16: 25000 | E16: 0
A17: 小額成本15,000 | B17: 27000 | C17: 15000 | D17: 25000 | E17: 0
A18: 區院成本40,000 | B18: 32000 | C18: 40000 | D18: 100000 | E18: 40000
A20: 小額低成本臨界p | B20: =IF(SUM(D16:E16)>0,(B16-C16)/SUM(D16:E16),"無可用分母") -> 0.88 | E20: 示例不代表本案敗訴機率。
A21: 小額較高成本臨界p | B21: =IF(SUM(D17:E17)>0,(B17-C17)/SUM(D17:E17),"無可用分母") -> 0.48 | E21: 示例不代表本案敗訴機率。
A22: 區院分支臨界p | B22: =IF(SUM(D18:E18)>0,(B18-C18)/SUM(D18:E18),"無可用分母") -> -0.057142857 | E22: 負數表示在這組假設下，即使勝訴成本也較高。

Sheet 判例來源
A1: 香港判例金額
A2: 當年港幣；實際判賠、替代評估、私人和解及訟費分開。沒有作2026通脹更新。
A4: 案件／日期 | B4: 實際PSLA | C4: 實際損害總額 | D4: 性質 | E4: 來源限制 | F4: 判詞來源
A5: Leung Ka Yee 2003-10-22 | B5: 75000 | C5: 78880 | D5: 法院評估 | E5: IPL背部，持續色素疤痕，欠交答辯。 | F5: https://babelcite.com/case/35934
A6: Shabbina Khokhar 2008-01-04 | B6: 120000 | C6: 160310 | D6: 法院評估 | E6: IPL雙臂及永久疤痕，婚禮影響；250,000是要求額。 | F6: https://babelcite.com/case/59829
A7: Chan Wai Yee Emily 2010-09-30 | B7: 150000 | C7: 178350 | D7: 法院評估 | E7: 腿部永久疤痕，責任承認。 | F7: https://babelcite.com/case/73182
A8: Chan Sze Ki 2011-01-07 | B8: 80000 | C8: 97519.65 | D8: 法院評估 | E8: 前臂IPL、殘留色差，醫療500並非總賠償。 | F8: https://babelcite.com/case/74738
A9: Xie Qiuyun 2015-12-18 | B9: 0 | C9: 0 | D9: 原告敗訴 | E9: 50,000 PSLA及78,000總額僅替代評估，非應付判賠。 | F9: https://babelcite.com/case/101901
A10: Luo Yurong 2021-06-28 | B10: 200000 | C10: 296045 | D10: 法院評估 | E10: 額部注射壞死永久疤痕，非激光。 | F10: https://babelcite.com/case/136803
A11: Leung Yuk Kwan 2002-12-04 | B11: 300000 | C11: 847949.75 | D11: 法院評估 | E11: 電熱灼傷、精神科及收入損失，非短暫小傷。 | F11: https://babelcite.com/case/25657
A12: Kwan Kam Ping 2026-01-22 | B12: 0 | C12: 0 | D12: 原告敗訴 | E12: 10,000及10,380僅替代評估；2026-10-05後續見報告。 | F12: https://babelcite.com/case/176578
A13: Ko Fung 2012-06-12 | D13: 客戶和解255,000 | E13: 客戶訟費120,000另計，供應商追償445,000不能當人傷判賠。 | F13: https://babelcite.com/case/82153
A16: 成本、工時、機率及保險 | B16: 均為假設／待填 | E16: 詳細定義見本套財務報告，沒有取得2026律師報價。
A17: 小額管轄 | E17: Cap.338第5條及附表涵蓋限額內侵權金錢申索；不一般排除人傷。 | F17: https://www.elegislation.gov.hk/hk/cap338!en
A18: 小額程序 | E18: 一般聆訊不得律師代表，成本與區院不同。 | F18: https://www.judiciary.hk/en/court_services_facilities/sc.html
